{
  "id": 15846919378,
  "names": {
    "default": "Five Nights TD",
    "clean": "Five Nights TD",
    "short": "FNTD"
  },
  "gamepasses": {
    "755213386": "VIP",
    "970374466": "Shiny Hunter",
    "1232238756": "Starter Pack & Exclusive Title"
  },
  "badges": {
    "450768915498982": "Join The Game",
    "3361299059765": "Win a Game",
    "1801557447657311": "Complete Game 1",
    "660308672766666": "Complete Game 2",
    "1249525436995984": "Finish Game 3",
    "1352734224772502": "Complete Game 4",
    "3840686186033460": "Complete Game 5",
    "1289932523675224": "Complete Game 6",
    "890542128167403": "Completed game 7",
    "4360266057339738": "Completed game 8",
    "1323923615523391": "Completed Game 10",
    "2308722040924793": "The ARG 1",
    "4348953112147721": "ARG 2 Winner",
    "4093753784951799": "Play Summer Event",
    "4192377969805376": "Complete Summer Event",
    "3717054685843370": "Play Military Event",
    "1710710467179779": "Complete Military Event",
    "78638580451212": "Play Wild West Event",
    "4427897814216895": "Finish Wild West",
    "481777508062526": "Play Halloween Event",
    "314612341496152": "Complete Halloween Event",
    "2794698248016894": "Played Steampunk Event",
    "4321640724737709": "Completed Steampunk Event",
    "2924114884782147": "Played Christmas Event!",
    "2486341879016297": "Completed Christmas Event",
    "1350170603923805": "Fools Hunt Winner",
    "1462238683858305": "Play Prehistoric Event",
    "477734488413301": "Complete Prehistoric Event",
    "3554984265461704": "Claim Calender Special Reward"
  }
}